{"shared_servicios_recordatorios-nginx.md":"uiwnX94T","servicios_gitea.md":"Ff7RBFvH","servicios_authentik.md":"MQHkCNb_","servicios_mailserver.md":"3yQniet_","servicios_homarr.md":"DorTqzHD","relatos_bloqueo-ssh.md":"DqJnZWiQ","relatos_usuario-docker.md":"v1x_n7fC","index.md":"F2ZW4fup","equipo_router-dominio.md":"LTpJWcnl","equipo_docker.md":"KPjWo-7R","servicios_dozzle.md":"0BQbGibv","equipo_mariadb-docker.md":"6bLS_tkv","servicios_minio.md":"V79vU11F","servicios_navidrome.md":"ngSAATDk","servicios_docker-mailserver.md":"vyFwLLp8","equipo_gestion-remota.md":"9kSbGCUh","equipo_nginx.md":"NAbMZqcj","servicios_uptime-kuma.md":"x5X99uuY","shared_servicios_puertos.md":"di7AIKC7","equipo_historia.md":"nvsUJ-AO","equipo_conectando-servidores.md":"YpnDsXsu","servicios_minecraft.md":"w612U4jZ","equipo_sistema-encriptado.md":"zLyqrr2t","servicios_sharelatex.md":"QJpXKR5S","relatos_dns-initramfs.md":"uo9S9Jg9","servicios_nextcloud.md":"sPNt_HFu","equipo_hardware.md":"w1XJVmme"}
